bob/__init__.py
bob/measure/__init__.py
bob/measure/_library.py
bob/measure/calibration.py
bob/measure/load.py
bob/measure/plot.py
bob/measure/utils.py
bob/measure/script/__init__.py
bob/measure/script/commands.py
bob/measure/script/common_options.py
bob/measure/script/figure.py
bob/measure/script/gen.py
bob/measure/script/measure.py
bob.measure-6.1.1.dist-info/LICENSE
bob.measure-6.1.1.dist-info/METADATA
bob.measure-6.1.1.dist-info/WHEEL
bob.measure-6.1.1.dist-info/entry_points.txt
bob.measure-6.1.1.dist-info/top_level.txt
bob.measure-6.1.1.dist-info/RECORD
