Metadata-Version: 2.1
Name: bob.measure
Version: 6.1.1
Summary: Evaluation metrics for Bob
Author-email: Andre Anjos <andre.anjos@idiap.ch>
License: BSD 3-Clause License
Project-URL: documentation, https://www.idiap.ch/software/bob/docs/bob/bob.measure/v6.1.1/sphinx/
Project-URL: homepage, https://pypi.org/project/bob.measure/
Project-URL: repository, https://gitlab.idiap.ch/bob/bob.measure
Project-URL: changelog, https://gitlab.idiap.ch/bob/bob.measure/-/releases
Keywords: bob,pipelines
Classifier: Framework :: Bob
Classifier: Development Status :: 4 - Beta
Classifier: Intended Audience :: Developers
Classifier: License :: OSI Approved :: BSD License
Classifier: Natural Language :: English
Classifier: Programming Language :: Python
Classifier: Programming Language :: Python :: 3
Classifier: Topic :: Software Development :: Libraries :: Python Modules
Requires-Python: >=3.9
License-File: LICENSE
Requires-Dist: bob ==12.1.1
Requires-Dist: bob.io.base ==5.1.1
Requires-Dist: clapper ~=1.0
Requires-Dist: h5py ~=3.7
Requires-Dist: matplotlib ~=3.8
Requires-Dist: numba ~=0.56
Requires-Dist: numpy ~=1.26
Requires-Dist: scipy ~=1.10
Requires-Dist: tabulate ~=0.9
Provides-Extra: doc
Requires-Dist: sphinx ; extra == 'doc'
Requires-Dist: sphinx-rtd-theme ; extra == 'doc'
Requires-Dist: sphinx-autodoc-typehints ; extra == 'doc'
Requires-Dist: auto-intersphinx ; extra == 'doc'
Requires-Dist: sphinxcontrib-programoutput ; extra == 'doc'
Requires-Dist: matplotlib ; extra == 'doc'
Provides-Extra: qa
Requires-Dist: pre-commit ; extra == 'qa'
Provides-Extra: test
Requires-Dist: pytest ; extra == 'test'
Requires-Dist: pytest-cov ; extra == 'test'
Requires-Dist: coverage ; extra == 'test'
